yaroslavslogger-0.9.0.dist-info/RECORD
yaroslavslogger-0.9.0.dist-info/METADATA
yaroslavslogger-0.9.0.dist-info/top_level.txt
yaroslavslogger-0.9.0.dist-info/WHEEL
yaroslavslogger-0.9.0.dist-info/LICENSE
yaroslavslogger/__init__.py
yaroslavslogger/mlog.py
yaroslavslogger/utilmodule.c
yaroslavslogger/utilmodule.cpython-310-x86_64-linux-gnu.so
yaroslavslogger/greetings.py
yaroslavslogger/compiled_libraries/libstring_length.so
