Metadata-Version: 2.1
Name: yaroslavslogger
Version: 0.9.0
Summary: A simple package with a greeting function
Home-page: UNKNOWN
Author: Your Name
Author-email: your.email@example.com
License: UNKNOWN
Platform: UNKNOWN
Classifier: Programming Language :: Python :: 3
Classifier: Programming Language :: C
Classifier: Operating System :: POSIX :: Linux
Requires-Python: >=3.6
License-File: LICENSE
